./LICENSE
./PKG-INFO
./README.md
./master_of_secrets.py
./pyproject.toml
./.idea/master-of-secrets.iml
./.idea/misc.xml
./.idea/modules.xml
./.idea/vcs.xml
./.idea/workspace.xml
./.idea/inspectionProfiles/profiles_settings.xml
master_of_secrets-0.1.1.dist-info/METADATA
master_of_secrets-0.1.1.dist-info/WHEEL
master_of_secrets-0.1.1.dist-info/entry_points.txt
master_of_secrets-0.1.1.dist-info/licenses/LICENSE
master_of_secrets-0.1.1.dist-info/RECORD
