Metadata-Version: 2.4
Name: master-of-secrets
Version: 0.1.1
Summary: Cryptographically secure Password Generator
Project-URL: Homepage, https://github.com/thelazybastard/the-master-of-secrets
Project-URL: Issues, https://github.com/thelazybastard/the-master-of-secrets/issues
Author-email: thelazybastard <0q2m4o1uq@mozmail.com>
License: MIT
License-File: LICENSE
Keywords: cli,cryptography,generator,password,security
Classifier: License :: OSI Approved :: MIT License
Classifier: Operating System :: OS Independent
Classifier: Programming Language :: Python :: 3
Classifier: Programming Language :: Python :: 3.9
Classifier: Programming Language :: Python :: 3.10
Classifier: Programming Language :: Python :: 3.11
Classifier: Programming Language :: Python :: 3.12
Classifier: Topic :: Security
Classifier: Topic :: Utilities
Requires-Python: >=3.9
Requires-Dist: numpy
Requires-Dist: scipy
